{"type":"PR","pr":{"number":895,"head":"92f8d54911a0d3df568812469b5fc96e5276f41d"},"user":"Lynn Chalati","status":"draft","branch":"cms/analyste-des-politiques","collection":"travaillez-avec-nous","title":"Analyste des politiques (étudiant)","description":"L’équipe des politiques du Service numérique canadien (SNC) est à la recherche d’un analyste des politiques pour soutenir les équipes chargées de la prestation des services numériques et contribuer à la stratégie de l’organisation (poste d’étudiant pour l’automne 2019).","objects":{"entry":{"path":"content/fr/work-with-us/positions/analyste-des-politiques.md","sha":"bab835f85666bd2c764438fbc1b0d3807cae08e9"},"files":[]},"timeStamp":"2019-07-11T14:08:52.910Z"}