{"type":"PR","pr":{"number":1272,"head":"3b317bff00cf863471aa727ece8357689dbe5c9a"},"user":"Victoria Chan","status":"pending_publish","branch":"cms/answering-your-questions-about-our-new-platform-to-send-government-emails-and-sms-messages","collection":"blog","title":"Answering your questions about our new platform to send government emails and SMS messages ","description":"Since we introduced our Notify platform, we’ve received many questions about how it works, who can use it, and most frequently, whether or not it's free. With such great interest around the platform, we wanted to take the time to answer your questions and encourage more organizations to bring their live services onto Notify. ","objects":{"entry":{"path":"content/en/blog/posts/answering-your-questions-about-our-new-platform-to-send-government-emails-and-sms-messages.md","sha":"10f212aa4ac03575861ac5fdf06352d2837f7347"},"files":[]},"timeStamp":"2020-02-18T18:43:24.786Z"}