{"type":"PR","pr":{"number":898,"head":"a53b0804c1483338f8daa7a4a7b9e6ba14cbf6f2"},"user":"Charcharbinkz","status":"draft","branch":"cms/données-qualitatives-inconfortables-oui-mais-elles-valent-le-coup","collection":"blogue","title":"Données qualitatives : inconfortables, oui, mais elles valent le coup","description":"Reconnaissons la valeur des données qualitatives afin de concevoir un service facile à comprendre et utile permettant aux membres du public de signaler un cybercrime. ","objects":{"entry":{"path":"content/fr/blog/posts/données-qualitatives-inconfortables-oui-mais-elles-valent-le-coup.md","sha":"c7d88670b15ee9a7a6d3871fdf59f575260016ee"},"files":[]},"timeStamp":"2019-07-11T16:45:08.434Z"}