{"type":"PR","pr":{"number":486,"head":"f2898ca66d74f2601beb841ddd44cc1ad0e4e974"},"user":"Lynn Chalati","status":"draft","branch":"cms/executive-assistant","collection":"work-with-us","title":"Executive Assistant","description":"CDS is looking for an executive assistant to work alongside members of our executive team. Do you have a natural inclination toward logistics and planning? Are you the type of person who jumps in with both feet when it comes to taking on new tasks and projects? Do you thrive at handling multiple demands in a rapidly changing environment? Are you collaborative and great to work with? Are you bilingual and love working in both official languages? Are you looking for a job with lots of challenges and room for growth? Can you separate the wheat from the chaff when it comes to a busy schedule and inbox?","objects":{"entry":{"path":"content/en/work-with-us/positions/executive-assistant.md","sha":"6a60d8b60e577ea85832c2821916493e65540221"},"files":[]},"timeStamp":"2019-01-11T15:36:41.468Z"}