{"type":"PR","pr":{"number":398,"head":"6a3a81e5648f415b8b97bc805ca1493bb24247f5"},"user":"anikbrazeau","status":"pending_publish","branch":"cms/head-of-outreach","collection":"work-with-us","title":"Head of Outreach","description":"As the Outreach Team, we are the storytellers of the CDS. We tell the stories that help public servants improve government services and make people’s lives better. But, we don't just tell feel-good stories. The problems we tackle are complex, and so are the stories we tell. We are not afraid to talk about what worked, what didn't, and how we can do it better. There are no villains in the stories we tell - we’re committed to understanding everyone’s needs and working through problems with them. If you’re ready to bring an open and personal voice to government then this is the role for you. ","objects":{"entry":{"path":"content/en/work-with-us/positions/head-of-outreach.md","sha":"23fb575587962c1a1d443d4a460314a333111678"},"files":[]},"timeStamp":"2018-11-25T19:07:12.545Z"}